coronastat/__init__.py
coronastat/corona.py
coronastat/driver.py
coronastat/proxy.py
coronastat/utils.py
coronastat-1.0.3.dist-info/LICENSE
coronastat-1.0.3.dist-info/METADATA
coronastat-1.0.3.dist-info/WHEEL
coronastat-1.0.3.dist-info/entry_points.txt
coronastat-1.0.3.dist-info/top_level.txt
coronastat-1.0.3.dist-info/RECORD
