Metadata-Version: 2.1
Name: coronastat
Version: 1.0.3
Summary: A python package to display countrywise and statewise ( India ) statistics of coronavirus ( COVID-19 ) in the terminal in tabular fashion
Home-page: https://github.com/theNocturnalGuy/coronastat
Author: Rahul Gupta
Author-email: rahulgupta0097@gmail.com
License: MIT
Platform: UNKNOWN
Classifier: License :: OSI Approved :: MIT License
Classifier: Programming Language :: Python :: 3
Classifier: Programming Language :: Python :: 3.5
Classifier: Programming Language :: Python :: 3.7
Requires-Dist: requests
Requires-Dist: terminaltables
Requires-Dist: bs4
